<mediawiki xmlns="http://www.mediawiki.org/xml/export-0.11/" xmlns:xsi="http://www.w3.org/2001/XMLSchema-instance" xsi:schemaLocation="http://www.mediawiki.org/xml/export-0.11/ http://www.mediawiki.org/xml/export-0.11.xsd" version="0.11" xml:lang="en">
  <siteinfo>
    <sitename>MediaWiki</sitename>
    <dbname>mediawikiwiki</dbname>
    <base>https://www.mediawiki.org/wiki/MediaWiki</base>
    <generator>MediaWiki 1.43.0-wmf.8</generator>
    <case>first-letter</case>
    <namespaces>
      <namespace key="-2" case="first-letter">Media</namespace>
      <namespace key="-1" case="first-letter">Special</namespace>
      <namespace key="0" case="first-letter" />
      <namespace key="1" case="first-letter">Talk</namespace>
      <namespace key="2" case="first-letter">User</namespace>
      <namespace key="3" case="first-letter">User talk</namespace>
      <namespace key="4" case="first-letter">Project</namespace>
      <namespace key="5" case="first-letter">Project talk</namespace>
      <namespace key="6" case="first-letter">File</namespace>
      <namespace key="7" case="first-letter">File talk</namespace>
      <namespace key="8" case="first-letter">MediaWiki</namespace>
      <namespace key="9" case="first-letter">MediaWiki talk</namespace>
      <namespace key="10" case="first-letter">Template</namespace>
      <namespace key="11" case="first-letter">Template talk</namespace>
      <namespace key="12" case="first-letter">Help</namespace>
      <namespace key="13" case="first-letter">Help talk</namespace>
      <namespace key="14" case="first-letter">Category</namespace>
      <namespace key="15" case="first-letter">Category talk</namespace>
      <namespace key="90" case="first-letter">Thread</namespace>
      <namespace key="91" case="first-letter">Thread talk</namespace>
      <namespace key="92" case="first-letter">Summary</namespace>
      <namespace key="93" case="first-letter">Summary talk</namespace>
      <namespace key="100" case="first-letter">Manual</namespace>
      <namespace key="101" case="first-letter">Manual talk</namespace>
      <namespace key="102" case="first-letter">Extension</namespace>
      <namespace key="103" case="first-letter">Extension talk</namespace>
      <namespace key="104" case="first-letter">API</namespace>
      <namespace key="105" case="first-letter">API talk</namespace>
      <namespace key="106" case="first-letter">Skin</namespace>
      <namespace key="107" case="first-letter">Skin talk</namespace>
      <namespace key="486" case="first-letter">Data</namespace>
      <namespace key="487" case="first-letter">Data talk</namespace>
      <namespace key="710" case="first-letter">TimedText</namespace>
      <namespace key="711" case="first-letter">TimedText talk</namespace>
      <namespace key="828" case="first-letter">Module</namespace>
      <namespace key="829" case="first-letter">Module talk</namespace>
      <namespace key="1198" case="first-letter">Translations</namespace>
      <namespace key="1199" case="first-letter">Translations talk</namespace>
      <namespace key="2600" case="first-letter">Topic</namespace>
      <namespace key="5500" case="first-letter">Newsletter</namespace>
      <namespace key="5501" case="first-letter">Newsletter talk</namespace>
    </namespaces>
  </siteinfo>
</mediawiki>
